mcp_gateway/__init__.py
mcp_gateway/config.py
mcp_gateway/gateway.py
mcp_gateway/sanitizers.py
mcp_gateway/server.py
mcp_gateway/plugins/__init__.py
mcp_gateway/plugins/base.py
mcp_gateway/plugins/manager.py
mcp_gateway/plugins/guardrails/__init__.py
mcp_gateway/plugins/guardrails/basic.py
mcp_gateway/plugins/guardrails/lasso.py
mcp_gateway/plugins/guardrails/presidio.py
mcp_gateway/plugins/tracing/__init__.py
mcp_gateway/plugins/tracing/xetrack.py
mcp_gateway/security_scanner/__init__.py
mcp_gateway/security_scanner/config.py
mcp_gateway/security_scanner/github_collector.py
mcp_gateway/security_scanner/npm_collector.py
mcp_gateway/security_scanner/project_analyzer.py
mcp_gateway/security_scanner/scanner.py
mcp_gateway/security_scanner/smithery_collector.py
mcp_gateway/security_scanner/tool_poisoning_analyzer.py
mcp_gateway-1.1.0.dist-info/licenses/LICENSE
mcp_gateway-1.1.0.dist-info/METADATA
mcp_gateway-1.1.0.dist-info/WHEEL
mcp_gateway-1.1.0.dist-info/entry_points.txt
mcp_gateway-1.1.0.dist-info/top_level.txt
mcp_gateway-1.1.0.dist-info/RECORD
