Metadata-Version: 2.4
Name: mcp-gateway
Version: 1.1.0
Summary: A gateway for MCP servers
License-Expression: MIT
Classifier: Development Status :: 4 - Beta
Classifier: Intended Audience :: Developers
Classifier: Programming Language :: Python :: 3
Classifier: Programming Language :: Python :: 3.10
Classifier: Programming Language :: Python :: 3.11
Classifier: Programming Language :: Python :: 3.12
Classifier: Programming Language :: Python :: 3.13
Classifier: Operating System :: OS Independent
Classifier: Topic :: Software Development :: Libraries :: Python Modules
Classifier: Topic :: Internet :: WWW/HTTP :: HTTP Servers
Classifier: Topic :: System :: Networking
Requires-Python: >=3.10
License-File: LICENSE
Requires-Dist: beautifulsoup4>=4.13.4
Requires-Dist: mcp[cli]>=1.6.0
Requires-Dist: requests>=2.32.3
Provides-Extra: dev
Requires-Dist: pytest>=7.0.0; extra == "dev"
Requires-Dist: pytest-asyncio>=0.21.0; extra == "dev"
Requires-Dist: pytest-cov>=4.1.0; extra == "dev"
Provides-Extra: presidio
Requires-Dist: presidio-anonymizer>=2.2.0; extra == "presidio"
Requires-Dist: presidio-analyzer>=2.2.0; extra == "presidio"
Provides-Extra: xetrack
Requires-Dist: xetrack>=0.3.4; extra == "xetrack"
Dynamic: license-file
